{
  "data": [
    {
      "name": "Ahmed Ihsan",
      "age": "19",
      "number": "07704893933",
      "date": "2021-06-19",
      "check": "Lemon",
      "result": "Working as well",
      "id": 1
    },
    {
      "name": "Redwan Faris",
      "age": "20",
      "number": "07705433322",
      "date": "2021-06-19",
      "check": "Back End",
      "result": "You Dead",
      "id": 2
    },
    {
      "name": "testttttt",
      "age": "23",
      "number": "595959",
      "date": "2021-06-15",
      "check": "testtt",
      "result": [
        {
          "name": "111111",
          "id": 55
        }
      ],
      "id": 4922.523325440111
    },
    {
      "patientName": "asdfghk",
      "patientAge": "7656",
      "patientPhoneNumber": "67",
      "testDate": "2021-06-28",
      "testResults": [
        {
          "id": "22",
          "firstTestResult": "uiydutdut",
          "secondTestResult": "iyvdeiyged"
        },
        {
          "id": "55",
          "firstTestResult": "dwouufgwd",
          "secondTestResult": "wdiyyfwdi"
        }
      ],
      "id": 4923.523325440111
    }
  ]
}